superjsonmode/__init__.py
superjsonmode/data/__init__.py
superjsonmode/data/parser.py
superjsonmode/data/prompts.py
superjsonmode/data/utils.py
superjsonmode/evals/__init__.py
superjsonmode/evals/eval_json.py
superjsonmode/evals/run_benchmarks.py
superjsonmode/integrations/__init__.py
superjsonmode/integrations/base_integration.py
superjsonmode/integrations/ollama.py
superjsonmode/integrations/openai.py
superjsonmode/integrations/transformers.py
superjsonmode/integrations/vllm.py
super_json_mode-0.1.2.dist-info/METADATA
super_json_mode-0.1.2.dist-info/WHEEL
super_json_mode-0.1.2.dist-info/top_level.txt
super_json_mode-0.1.2.dist-info/RECORD
