Metadata-Version: 2.1
Name: super-json-mode
Version: 0.1.2
Summary: A framework for faster structured output generation using LLMs.
Home-page: https://github.com/varunshenoy/super-json-mode
Author: Varun Shenoy
Author-email: vnshenoy@stanford.edu
Requires-Dist: prettytable ==3.9.0
Requires-Dist: pydantic ==2.5.2
Requires-Dist: tqdm
Requires-Dist: transformers ==4.37.2
Requires-Dist: openai ==1.11.1
